rscm/__init__.py
rscm/_lib/__init__.pyi
rscm/_lib/calibrate.pyi
rscm/_lib/components.pyi
rscm/_lib/core/__init__.pyi
rscm/_lib/core/spatial.pyi
rscm/_lib/core/state.pyi
rscm/_lib/magicc.pyi
rscm/_lib/two_layer.pyi
rscm/_lib.abi3.so
rscm/calibrate/__init__.py
rscm/calibrate/pandas_helpers.py
rscm/calibrate/progress.py
rscm/component.py
rscm/components.py
rscm/core.py
rscm/example_components.py
rscm/magicc/__init__.py
rscm/py.typed
rscm/two_layer/__init__.py
rscm-0.5.0.dist-info/METADATA
rscm-0.5.0.dist-info/WHEEL
rscm-0.5.0.dist-info/licenses/LICENSE
rscm-0.5.0.dist-info/RECORD
