Metadata-Version: 2.4
Name: rscm
Version: 0.5.0
Classifier: Development Status :: 3 - Alpha
Classifier: Intended Audience :: Science/Research
Classifier: License :: OSI Approved :: Apache Software License
Classifier: Programming Language :: Python :: 3
Classifier: Programming Language :: Python :: 3.11
Classifier: Programming Language :: Python :: 3.12
Classifier: Programming Language :: Python :: 3.13
Classifier: Programming Language :: Rust
Classifier: Topic :: Scientific/Engineering :: Atmospheric Science
Requires-Dist: numpy
Requires-Dist: pandas
License-File: LICENSE
Summary: Simple Climate Model framework implemented in Rust
Keywords: climate,climate-model,scm,physics,rust
Author-email: Jared Lewis <jared.lewis@climate-energy-college.org>
License: Apache-2.0
Requires-Python: >=3.11
Project-URL: Documentation, https://lewisjared.github.io/rscm/
Project-URL: Homepage, https://github.com/lewisjared/rscm
Project-URL: Repository, https://github.com/lewisjared/rscm
